diagnostic_msgs/_dummy.cpython-313-x86_64-linux-gnu.so
ros_diagnostic_msgs-5.5.1.data/data/include/diagnostic_msgs/diagnostic_msgs/msg/diagnostic_array.h
ros_diagnostic_msgs-5.5.1.data/data/include/diagnostic_msgs/diagnostic_msgs/msg/diagnostic_array.hpp
ros_diagnostic_msgs-5.5.1.data/data/include/diagnostic_msgs/diagnostic_msgs/msg/diagnostic_status.h
ros_diagnostic_msgs-5.5.1.data/data/include/diagnostic_msgs/diagnostic_msgs/msg/diagnostic_status.hpp
ros_diagnostic_msgs-5.5.1.data/data/include/diagnostic_msgs/diagnostic_msgs/msg/key_value.h
ros_diagnostic_msgs-5.5.1.data/data/include/diagnostic_msgs/diagnostic_msgs/msg/key_value.hpp
ros_diagnostic_msgs-5.5.1.data/data/include/diagnostic_msgs/diagnostic_msgs/msg/rosidl_generator_c__visibility_control.h
ros_diagnostic_msgs-5.5.1.data/data/include/diagnostic_msgs/diagnostic_msgs/msg/rosidl_generator_cpp__visibility_control.hpp
ros_diagnostic_msgs-5.5.1.data/data/include/diagnostic_msgs/diagnostic_msgs/msg/rosidl_typesupport_fastrtps_c__visibility_control.h
ros_diagnostic_msgs-5.5.1.data/data/include/diagnostic_msgs/diagnostic_msgs/msg/rosidl_typesupport_fastrtps_cpp__visibility_control.h
ros_diagnostic_msgs-5.5.1.data/data/include/diagnostic_msgs/diagnostic_msgs/msg/rosidl_typesupport_introspection_c__visibility_control.h
ros_diagnostic_msgs-5.5.1.data/data/include/diagnostic_msgs/diagnostic_msgs/msg/detail/diagnostic_array__builder.hpp
ros_diagnostic_msgs-5.5.1.data/data/include/diagnostic_msgs/diagnostic_msgs/msg/detail/diagnostic_array__description.c
ros_diagnostic_msgs-5.5.1.data/data/include/diagnostic_msgs/diagnostic_msgs/msg/detail/diagnostic_array__functions.c
ros_diagnostic_msgs-5.5.1.data/data/include/diagnostic_msgs/diagnostic_msgs/msg/detail/diagnostic_array__functions.h
ros_diagnostic_msgs-5.5.1.data/data/include/diagnostic_msgs/diagnostic_msgs/msg/detail/diagnostic_array__rosidl_typesupport_fastrtps_c.h
ros_diagnostic_msgs-5.5.1.data/data/lib/python3.13/site-packages/diagnostic_msgs-5.5.1-py3.13.egg-info/PKG-INFO
ros_diagnostic_msgs-5.5.1.data/data/lib/python3.13/site-packages/diagnostic_msgs-5.5.1-py3.13.egg-info/SOURCES.txt
ros_diagnostic_msgs-5.5.1.data/data/lib/python3.13/site-packages/diagnostic_msgs-5.5.1-py3.13.egg-info/dependency_links.txt
ros_diagnostic_msgs-5.5.1.data/data/lib/python3.13/site-packages/diagnostic_msgs-5.5.1-py3.13.egg-info/top_level.txt
ros_diagnostic_msgs-5.5.1.dist-info/METADATA
ros_diagnostic_msgs-5.5.1.dist-info/WHEEL
ros_diagnostic_msgs-5.5.1.dist-info/top_level.txt
ros_diagnostic_msgs-5.5.1.dist-info/RECORD
ros_diagnostic_msgs-5.5.1.dist-info/licenses/LICENSE
