Metadata-Version: 2.4
Name: ros-diagnostic-msgs
Version: 5.5.1
Summary: ROS package `diagnostic_msgs` provides messages and services for node and robot diagnostics, including status and self-tests.
License-File: LICENSE
Requires-Dist: ros-rosidl-default-runtime~=1.7.1
Requires-Dist: ros-geometry-msgs~=5.5.1
Requires-Dist: ros-builtin-interfaces~=2.3.0
Requires-Dist: ros-std-msgs~=5.5.1
Dynamic: description
Dynamic: description-content-type
Dynamic: license-file
Dynamic: requires-dist
Dynamic: summary
